{
    "title": "中性反馈",
    "introduction": null,
    "icon": "gpt",
    "parts": [
        {
            "title": "形态结构",
            "steps": [
                {
                    "type": "chat",
                    "content": "流行性感冒是由流感病毒所引起的一种常见呼吸道疾病。流感病毒可以分为 甲，乙，丙，丁四型。其中，人类流感主要是由甲型和乙型流感病毒引起。",
                    "picture": "1-1"
                },                
                {
                    "type": "chat",
                    "content": "流感病毒的外观呈球形，自外而内可以分为“包膜”，“基质蛋白”以及病毒核心三个部分。",
                    "picture": "1-2"
                },                
                {
                    "type": "chat",
                    "content": "在病毒的包膜上有两种重要的蛋白质，数量较少且呈蘑菇状的叫做神经氨酸 酶“简称 NA”，数量较多呈杆状的叫做血凝素，简称“HA”。",
                    "picture": "1-3"
                },                
                {
                    "type": "chat",
                    "content": "上述两种蛋白质也被叫做作“表面抗原”。人体免疫系统通过病毒的抗原来判 断并记忆病毒的种类。当相同的病毒再次入侵时，免疫系统就能产生对应的 抗体来消灭入侵的病毒。 病毒学家则将不同的抗原分别编号命名，根据这一命名系统，同型的病毒也 可以被分为不同的亚型。例如，目前已知的甲型流感病毒总共有 135 种亚型。",
                    "picture": "1-4"
                },                
                {
                    "type": "chat",
                    "content": "当然，血凝素与神经氨酸酶的本来作用并不是给人体免疫系统提供靶子，或 是方便病毒学家进行分类。而是为了更方便的入侵人体。",
                    "picture": "1-5"
                },
                {
                    "type": "chat",
                    "content": "现在进行测试。"
                },
                {
                    "type": "single_choice",
                    "question": "关于流感病毒表面蛋白质的描述，下列哪项是正确的？",
                    "choices": [
                        "HA蛋白呈蘑菇状，数量较少；NA蛋白呈杆状，数量较多",
                        "HA蛋白呈杆状，数量较多；NA蛋白呈蘑菇状，数量较少",
                        "HA蛋白和NA蛋白都呈杆状，数量相等",
                        "HA蛋白和NA蛋白都呈蘑菇状，但作用不同"
                    ],
                    "correct_answer": ["B"],
                    "response": {
                        "correct": "选择正确",
                        "incorrect": "选择错误正确答案是B，血凝素(HA)呈杆状且数量较多，主要负责病毒与细胞表面受体的结合；神经氨酸酶(NA)呈蘑菇状且数量较少，主要负责帮助新病毒从宿主细胞脱离。这两种蛋白质的形态和数量差异反映了它们在病毒感染过程中的不同功能。"
                    }
                }
            ]
        },
        {
            "title": "感染过程",
            "steps": [
                {
                    "type": "chat",
                    "content": "流感病毒主要通过病毒飞沫进行传播。当人体吸入病毒后，它们会经由呼吸 道降落在鼻腔，咽喉甚至肺部的上皮细胞上。",
                    "picture": "2-1"
                }, 
                {
                    "type": "chat",
                    "content": "正常的细胞被一层细胞膜所包裹，细胞膜具有选择透过性。水和营养物质能 够透过细胞膜进入细胞内部，而其他物质则被阻挡在细胞膜之外。",
                    "picture": "2-2"
                }, 
                {
                    "type": "chat",
                    "content": "当病毒落在细胞表面时，病毒外部的血凝素会与细胞膜表面的唾液酸受体互 相结合，使得病毒牢牢吸附在细胞表面。",
                    "picture": "2-3"
                }, 
                {
                    "type": "chat",
                    "content": "随后，在血凝素的作用下，细胞膜会将病毒误认为某种营养物质，并将其包裹起来逐步送入体内。这一过程被称为“吞饮”。",
                    "picture": "2-4"
                }, 
                {
                    "type": "chat",
                    "content": "进入细胞后，病毒会从其核心释放出遗传物质和相关蛋白质，并劫持细胞的器官大量复制。新复制的遗传物质和蛋白质又会重新组合，从而形成新的病毒核心。",
                    "picture": "2-5"
                }, 
                {
                    "type": "chat",
                    "content": "新的病毒核心会逐渐靠近细胞膜。而宿主细胞的细胞膜会再次将新病毒核心包裹起来，形成一个完整的新病毒，并在细胞膜上造成一个凸起。但此时，病毒仍然与宿主细胞连接在一起。",
                    "picture": "2-6"
                }, 
                {
                    "type": "chat",
                    "content": "为了摆脱宿主细胞，新病毒表面的神经氨酸酶开始发挥作用，它与宿主细胞的细胞膜发生水解反应，从而溶解了细胞膜。自此，新病毒脱彻底离开了宿主细胞并得以继续感染其他正常细胞。",
                    "picture": "2-7"
                }, 
                {
                    "type": "chat",
                    "content": "整个病毒入侵过程会使得正常细胞变性，坏死。造成粘膜充血水肿，从而引发鼻塞，流涕，咽喉疼痛等症状。",
                    "picture": "2-8"
                },
                {
                    "type": "chat",
                    "content": "现在进行测试。"
                },
                {
                    "type": "single_choice",
                    "question": "流感病毒入侵和脱离宿主细胞的关键步骤是：",
                    "choices": [
                        "HA蛋白帮助病毒脱离，NA蛋白帮助病毒吸附",
                        "病毒直接穿透细胞膜进入，然后破坏细胞膜离开",
                        "HA蛋白与唾液酸受体结合实现吸附，NA蛋白水解细胞膜实现脱离",
                        "病毒通过胞间连丝进入细胞，通过胞吐作用离开"
                    ],
                    "correct_answer": ["C"],
                    "response": {
                        "correct": "选择正确",
                        "incorrect": "选择错误正确答案是C，流感病毒感染过程中，HA蛋白负责与细胞表面的唾液酸受体特异性结合，使病毒牢固吸附在细胞表面；而NA蛋白则在病毒复制完成后发挥水解酶作用，切断病毒与细胞膜的连接，帮助新病毒脱离宿主细胞。这种\"进入-复制-脱离\"的精确分工是流感病毒高效感染的关键。"
                    }
                }
            ]
        },
        {
            "title": "病毒变异",
            "steps": [
                {
                    "type": "chat",
                    "content": "流感病毒可以通过接种疫苗进行预防。但是流感病毒具有很强的抗药性，一次接种并不能一劳永逸的解决流感问题。",
                    "picture": "3-1"
                }, 
                {
                    "type": "chat",
                    "content": "引起流感病毒抗药性的根源在于病毒特殊的遗传物质。生物的遗传物质一般是脱氧核糖核酸，简称 DNA。而流感病毒采用核糖核酸，简称 RNA，作为遗传物质。",
                    "picture": "3-2"
                }, 
                {
                    "type": "chat",
                    "content": "DNA 在复制过程中有一套纠错机制，能够避免复制过程中的突变。而 RNA 则没有这种机制，因此，病毒复制过程中的任何变异都被保留了下来。",
                    "picture": "3-3"
                }, 
                {
                    "type": "chat",
                    "content": "一旦病毒的遗传物质发生突变，病毒表面的血凝素和神经氨酸酶就有可能发生改变。这种改变被称为“抗原漂移”或者“抗原改变”。",
                    "picture": "3-4"
                }, 
                {
                    "type": "chat",
                    "content": "人体免疫系统需要通过辨别病毒的表面抗原来判断病毒的类型。一旦发生抗原改变，新的病毒对于免疫系统而言就是完全陌生的了。免疫系统也就无法 产生针对这张新病毒的抗体，只能任由它们在体内肆虐。",
                    "picture": "3-5"
                },
                {
                    "type": "chat",
                    "content": "现在进行测试。"
                },
                {
                    "type": "single_choice",
                    "question": "流感病毒容易发生变异的根本原因是：",
                    "choices": [
                        "流感病毒的DNA结构不稳定，容易断裂",
                        "流感病毒以RNA作为遗传物质，复制时缺乏纠错机制",
                        "流感病毒的蛋白质外壳经常发生物理性损伤",
                        "人体免疫系统的攻击导致病毒被迫改变结构"
                    ],
                    "correct_answer": ["B"],
                    "response": {
                        "correct": "选择正确",
                        "incorrect": "选择错误正确答案是B，与大多数生物使用DNA作为遗传物质不同，流感病毒使用RNA。DNA复制具有完善的纠错机制，能够及时发现并修正复制错误，保证遗传信息的准确传递；而RNA复制缺乏这种纠错机制，复制过程中产生的任何突变都会被保留下来。这使得流感病毒在每次复制时都可能产生新的变异，导致表面抗原发生改变，从而逃避免疫系统的识别。"
                    }
                }
            ]
        }
    ]
}